{
  "schema": 1,
  "id": "deep-dig",
  "title": "Deep Dig",
  "stages": [
    {
      "id": "d01",
      "board": [
        "........",
        "........",
        "........",
        ".66..66.",
        ".66..66.",
        "........",
        "66....66",
        "66....66"
      ],
      "goal": { "type": "score", "target": 200 }
    },
    {
      "id": "d02",
      "board": [
        "........",
        "..b.....",
        "..4.b...",
        "..44.b..",
        "..444...",
        "..4444..",
        "........",
        "........"
      ],
      "goal": { "type": "gems", "counts": { "blue": 3 } }
    },
    {
      "id": "d03",
      "board": [
        "7.7.7.7.",
        ".7.7.7.7",
        "7.7.7.7.",
        "........",
        "........",
        ".7.7.7.7",
        "7.7.7.7.",
        ".7.7.7.7"
      ],
      "goal": { "type": "score", "target": 300 }
    },
    {
      "id": "d04",
      "board": [
        "........",
        ".g....r.",
        ".11..11.",
        "........",
        "........",
        ".11..11.",
        ".r....g.",
        "........"
      ],
      "goal": { "type": "gems", "counts": { "green": 2, "red": 2 } }
    },
    {
      "id": "d05",
      "board": [
        "33333...",
        "3.......",
        "3.......",
        "3.......",
        "........",
        ".......3",
        ".......3",
        "...33333"
      ],
      "goal": { "type": "score", "target": 400 }
    },
    {
      "id": "d06",
      "board": [
        "...p....",
        "...5....",
        "p..5..p.",
        "...5....",
        "...p....",
        "........",
        "........",
        "........"
      ],
      "goal": { "type": "gems", "counts": { "purple": 4 } }
    },
    {
      "id": "d07",
      "board": [
        "........",
        ".000000.",
        ".0....0.",
        ".0....0.",
        ".0....0.",
        ".0....0.",
        ".000000.",
        "........"
      ],
      "goal": { "type": "score", "target": 500 }
    },
    {
      "id": "d08",
      "board": [
        "y......y",
        ".6....6.",
        "..6..6..",
        "...66...",
        "...66...",
        "..6..6..",
        ".6....6.",
        "y......."
      ],
      "goal": { "type": "gems", "counts": { "yellow": 3 } },
      "hard": true
    },
    {
      "id": "d09",
      "board": [
        ".1.1.1..",
        "1.1.1.1.",
        "........",
        ".2.2.2..",
        "2.2.2.2.",
        "........",
        ".3.3.3..",
        "3.3.3.3."
      ],
      "goal": { "type": "score", "target": 600 }
    },
    {
      "id": "d10",
      "board": [
        "..r..b..",
        "..1..1..",
        "........",
        "r......b",
        "1......1",
        "........",
        "..r.....",
        "..1....."
      ],
      "goal": { "type": "gems", "counts": { "red": 3, "blue": 2 } }
    },
    {
      "id": "d11",
      "board": [
        "44..44..",
        "44..44..",
        "..44..44",
        "..44..44",
        "44..44..",
        "44..44..",
        "..44..44",
        "..44..44"
      ],
      "goal": { "type": "score", "target": 700 },
      "hard": true
    },
    {
      "id": "d12",
      "board": [
        ".p....g.",
        ".5....1.",
        "........",
        ".g....p.",
        ".1....5.",
        "........",
        ".p....g.",
        ".5....1."
      ],
      "goal": { "type": "gems", "counts": { "purple": 3, "green": 3 } },
      "hard": true
    },
    {
      "id": "d13",
      "board": [
        "5555.555",
        "5......5",
        "5......5",
        "5......5",
        "........",
        "5......5",
        "5......5",
        "5555.555"
      ],
      "goal": { "type": "score", "target": 800 },
      "hard": true
    },
    {
      "id": "d14",
      "board": [
        "r...r...",
        ".1...1..",
        "..r...1.",
        "...1....",
        "....r...",
        ".....1..",
        "..1...r.",
        "........"
      ],
      "goal": { "type": "gems", "counts": { "red": 5 } },
      "hard": true
    },
    {
      "id": "d15",
      "board": [
        "..r.b...",
        "........",
        ".p...y..",
        "........",
        "....g...",
        "........",
        "..2...2.",
        ".222.22."
      ],
      "goal": {
        "type": "gems",
        "counts": { "red": 1, "blue": 1, "purple": 1, "yellow": 1, "green": 1 }
      },
      "hard": true
    }
  ]
}
